azure/mgmt/storageactions/__init__.py
azure/mgmt/storageactions/_client.py
azure/mgmt/storageactions/_configuration.py
azure/mgmt/storageactions/_patch.py
azure/mgmt/storageactions/_version.py
azure/mgmt/storageactions/py.typed
azure/mgmt/storageactions/_utils/__init__.py
azure/mgmt/storageactions/_utils/model_base.py
azure/mgmt/storageactions/_utils/serialization.py
azure/mgmt/storageactions/aio/__init__.py
azure/mgmt/storageactions/aio/_client.py
azure/mgmt/storageactions/aio/_configuration.py
azure/mgmt/storageactions/aio/_patch.py
azure/mgmt/storageactions/aio/operations/__init__.py
azure/mgmt/storageactions/aio/operations/_operations.py
azure/mgmt/storageactions/aio/operations/_patch.py
azure/mgmt/storageactions/models/__init__.py
azure/mgmt/storageactions/models/_enums.py
azure/mgmt/storageactions/models/_models.py
azure/mgmt/storageactions/models/_patch.py
azure/mgmt/storageactions/operations/__init__.py
azure/mgmt/storageactions/operations/_operations.py
azure/mgmt/storageactions/operations/_patch.py
azure_mgmt_storageactions-1.0.0.dist-info/LICENSE
azure_mgmt_storageactions-1.0.0.dist-info/METADATA
azure_mgmt_storageactions-1.0.0.dist-info/WHEEL
azure_mgmt_storageactions-1.0.0.dist-info/top_level.txt
azure_mgmt_storageactions-1.0.0.dist-info/RECORD
